{
  "error": true,
  "maintainers": [
    {
      "main_maintainer": true,
      "github_username": "KostyaJRZ",
      "name": "KostyaJRZ"
    }
  ],
  "donate_url": "",
  "website_url": "https://pixelplusui.github.io",
  "news_url": "https://t.me/ppuich",
  "datetime": 2614507540,
  "filename": "PixelPlusUI_3.2_onclite-11.0-20210228-1019-OFFICIAL.zip",
  "id": "e436ec7588e723addd149b00e3624c7b6a79d522f0d714fea6a20141e60e7740 ",
  "size": 1316745183,
  "url": "https://github.com/PixelPlusUI-Devices/device_xiaomi_onclite/releases/download/3.2/PixelPlusUI_3.2_onclite-11.0-20210228-1019-OFFICIAL.zip",
  "version": "Eleven",
  "filehash": "3d11d45543912ca75cf8ffb143243345"
}
